README.md
setup.cfg
setup.py
boomband/__init__.py
boomband/boomband.py
boomband.egg-info/PKG-INFO
boomband.egg-info/SOURCES.txt
boomband.egg-info/dependency_links.txt
boomband.egg-info/top_level.txt