Metadata-Version: 1.0
Name: boomband
Version: 0.1
Summary: Test for Boomband wifi service
Home-page: https://github.com/mzfr/package
Author: Mehtab zafar
Author-email: zafardaffer.6@gmail.com
License: UNKNOWN
Platform: UNKNOWN
